README.md
setup.cfg
setup.py
oblopy/__init__.py
oblopy/poblo.py
oblopy/retrieval.py
oblopy/roblo.py
oblopy/toblo.py
oblopy.egg-info/PKG-INFO
oblopy.egg-info/SOURCES.txt
oblopy.egg-info/dependency_links.txt
oblopy.egg-info/requires.txt
oblopy.egg-info/top_level.txt