Metadata-Version: 2.1
Name: oblopy
Version: 0.0.5
Summary: Python toolbox for reading, analysing and processing profiling Lidar observations.
Home-page: https://github.com/cdu022/oblopy
Author: Christiane Duscha
Author-email: christiane.duscha@uib.no
License: bsd-3-clause
Download-URL: https://github.com/cdu022/oblopy/archive/refs/tags/v0.0.5.tar.gz
Keywords: Offshore Boundary Layer Observatory (OBLO),Marine Boundary Layer,Lidar,Retrieval,Motion correction,meteorology,bergen
Platform: UNKNOWN
Classifier: Development Status :: 3 - Alpha
Classifier: Intended Audience :: Developers
Classifier: Topic :: Software Development :: Build Tools
Classifier: License :: OSI Approved :: BSD License
Classifier: Programming Language :: Python :: 3
Classifier: Programming Language :: Python :: 3.4
Classifier: Programming Language :: Python :: 3.5
Classifier: Programming Language :: Python :: 3.6
